CodernityDBPyClient
