Metadata-Version: 1.1
Name: CodernityDB-PyClient
Version: 0.4.0
Summary: Client library for CodernityDB-HTTP
Home-page: http://codernity.com
Author: Codernity
Author-email: contact@codernity.com
License: Apache 2.0
Platform: UNKNOWN
Classifier: License :: OSI Approved :: Apache Software License
Classifier: Programming Language :: Python :: 2.6
Classifier: Programming Language :: Python :: 2.7
Classifier: Operating System :: MacOS :: MacOS X
Classifier: Operating System :: POSIX
Classifier: Operating System :: Microsoft :: Windows
Classifier: Operating System :: OS Independent
Classifier: Topic :: Internet
Classifier: Topic :: Database
Classifier: Topic :: Software Development
Classifier: Intended Audience :: Developers
Classifier: Development Status :: 4 - Beta
